easy/__init__.py
easy/admin.py
easy/apps.py
easy/decorators.py
easy/exception.py
easy/main.py
easy/response.py
easy/utils.py
easy/conf/__init__.py
easy/conf/settings.py
easy/controller/__init__.py
easy/controller/auto_api.py
easy/controller/base.py
easy/controller/meta.py
easy/controller/meta_conf.py
easy/domain/__init__.py
easy/domain/base.py
easy/domain/meta.py
easy/domain/orm.py
easy/permissions/__init__.py
easy/permissions/adminsite.py
easy/permissions/base.py
easy/permissions/superuser.py
easy/renderer/__init__.py
easy/renderer/json.py
easy/services/__init__.py
easy/services/base.py
easy/services/crud.py
easy/services/permission.py
easy/testing/__init__.py
easy/testing/client.py
django_api_framework-0.2.0.dist-info/LICENSE
django_api_framework-0.2.0.dist-info/WHEEL
django_api_framework-0.2.0.dist-info/METADATA
django_api_framework-0.2.0.dist-info/RECORD
