Metadata-Version: 2.1
Name: django-api-framework
Version: 0.2.0
Summary: Django Easy API - Easy and Fast Django REST framework based on Django-ninja-extra
Home-page: https://github.com/freemindcore/django-api-framework
Author: Freemind Core
Author-email: freemindcore@icloud.com
Requires-Python: >=3.6
Classifier: Intended Audience :: Information Technology
Classifier: Intended Audience :: System Administrators
Classifier: Operating System :: OS Independent
Classifier: Topic :: Internet
Classifier: Topic :: Software Development :: Libraries :: Application Frameworks
Classifier: Topic :: Software Development :: Libraries :: Python Modules
Classifier: Topic :: Software Development :: Libraries
Classifier: Topic :: Software Development
Classifier: Typing :: Typed
Classifier: Environment :: Web Environment
Classifier: Intended Audience :: Developers
Classifier: License :: OSI Approved :: MIT License
Classifier: Programming Language :: Python :: 3
Classifier: Programming Language :: Python :: 3.6
Classifier: Programming Language :: Python :: 3.7
Classifier: Programming Language :: Python :: 3.8
Classifier: Programming Language :: Python :: 3.9
Classifier: Programming Language :: Python :: 3.10
Classifier: Programming Language :: Python :: 3.11
Classifier: Programming Language :: Python :: 3 :: Only
Classifier: Framework :: Django
Classifier: Framework :: Django :: 3.1
Classifier: Framework :: Django :: 3.2
Classifier: Framework :: Django :: 4.0
Classifier: Framework :: Django :: 4.1
Classifier: Framework :: Django :: 4.2
Classifier: Framework :: AsyncIO
Classifier: Topic :: Internet :: WWW/HTTP :: HTTP Servers
Classifier: Topic :: Internet :: WWW/HTTP
Requires-Dist: Django >= 3.1
Requires-Dist: django-ninja-extra >= 0.16.0
Requires-Dist: autoflake ; extra == "dev"
Requires-Dist: pre_commit ; extra == "dev"
Requires-Dist: bumpversion==0.6.0 ; extra == "dev"
Requires-Dist: mkdocs >=1.1.2,<2.0.0 ; extra == "doc"
Requires-Dist: mkdocs-material >=7.1.9,<8.0.0 ; extra == "doc"
Requires-Dist: mdx-include >=1.4.1,<2.0.0 ; extra == "doc"
Requires-Dist: mkdocs-markdownextradata-plugin >=0.1.7,<0.3.0 ; extra == "doc"
Requires-Dist: markdown-include ; extra == "doc"
Requires-Dist: pytest ; extra == "test"
Requires-Dist: pytest-cov ; extra == "test"
Requires-Dist: pytest-django ; extra == "test"
Requires-Dist: pytest-asyncio ; extra == "test"
Requires-Dist: black==23.10.1 ; extra == "test"
Requires-Dist: mypy==1.6.1 ; extra == "test"
Requires-Dist: isort ; extra == "test"
Requires-Dist: injector>= 0.19.0 ; extra == "test"
Requires-Dist: flake8 ; extra == "test"
Requires-Dist: django-stubs ; extra == "test"
Requires-Dist: factory-boy==3.2.1 ; extra == "test"
Requires-Dist: django_coverage_plugin ; extra == "test"
Requires-Dist: django-ninja-extra >= 0.20.0 ; extra == "test"
Requires-Dist: django-ninja-jwt>=5.2.9 ; extra == "test"
Requires-Dist: Django >= 3.1 ; extra == "test"
Project-URL: Documentation, https://github.com/freemindcore/django-api-framework
Provides-Extra: dev
Provides-Extra: doc
Provides-Extra: test
